equadratures/__init__.py
equadratures/basis.py
equadratures/correlations.py
equadratures/datasets.py
equadratures/optimisation.py
equadratures/parameter.py
equadratures/plot.py
equadratures/poly.py
equadratures/polynet.py
equadratures/polytree.py
equadratures/quadrature.py
equadratures/scalers.py
equadratures/solver.py
equadratures/stats.py
equadratures/subsampling.py
equadratures/subspaces.py
equadratures/weight.py
equadratures/distributions/__init__.py
equadratures/distributions/analytical.py
equadratures/distributions/beta.py
equadratures/distributions/cauchy.py
equadratures/distributions/chebyshev.py
equadratures/distributions/chi.py
equadratures/distributions/chisquared.py
equadratures/distributions/exponential.py
equadratures/distributions/gamma.py
equadratures/distributions/gaussian.py
equadratures/distributions/gumbel.py
equadratures/distributions/logistic.py
equadratures/distributions/lognormal.py
equadratures/distributions/pareto.py
equadratures/distributions/rayleigh.py
equadratures/distributions/recurrence_utils.py
equadratures/distributions/studentst.py
equadratures/distributions/template.py
equadratures/distributions/triangular.py
equadratures/distributions/truncated_gaussian.py
equadratures/distributions/uniform.py
equadratures/distributions/weibull.py
equadratures/sampling_methods/__init__.py
equadratures/sampling_methods/induced.py
equadratures/sampling_methods/montecarlo.py
equadratures/sampling_methods/sampling_template.py
equadratures/sampling_methods/sparsegrid.py
equadratures/sampling_methods/tensorgrid.py
equadratures/sampling_methods/userdefined.py
equadratures-9.1.0.2.dist-info/LICENSE
equadratures-9.1.0.2.dist-info/METADATA
equadratures-9.1.0.2.dist-info/WHEEL
equadratures-9.1.0.2.dist-info/top_level.txt
equadratures-9.1.0.2.dist-info/RECORD
