Metadata-Version: 2.1
Name: equadratures
Version: 9.1.0.2
Summary: Polynomial approximations
Home-page: https://github.com/Effective-Quadratures/equadratures
Author: Developers
License: LPGL-2.1
Keywords: polynomial chaos effective quadratures polynomial approximations gradients
Platform: UNKNOWN
Classifier: Programming Language :: Python :: 3.5
Classifier: Programming Language :: Python :: 3.6
Classifier: Programming Language :: Python :: 3.7
Classifier: Programming Language :: Python :: 3.8
Classifier: Programming Language :: Python :: 3.9
Classifier: Intended Audience :: Science/Research
Classifier: Topic :: Scientific/Engineering :: Mathematics
Requires-Dist: numpy
Requires-Dist: scipy (>=0.15.0)
Requires-Dist: matplotlib
Requires-Dist: seaborn
Requires-Dist: requests (>=2.11.1)
Requires-Dist: graphviz
Provides-Extra: cvxpy
Requires-Dist: cvxpy (>=1.1) ; extra == 'cvxpy'
